coo/__init__.py
coo/coo.py
coo/exceptions.py
coo/utils.py
coo-0.1.3.dist-info/LICENSE
coo-0.1.3.dist-info/METADATA
coo-0.1.3.dist-info/WHEEL
coo-0.1.3.dist-info/top_level.txt
coo-0.1.3.dist-info/RECORD
