Metadata-Version: 2.1
Name: coo
Version: 0.1.3
Summary: Schedule Twitter Updates with Easy
Home-page: https://github.com/wilfredinni/coo
Author: Carlos Montecinos Geisse
Author-email: carlos.w.montecinos@gmail.com
License: Apache Software License 2.0
Keywords: coo
Platform: UNKNOWN
Classifier: Development Status :: 2 - Pre-Alpha
Classifier: Intended Audience :: Developers
Classifier: License :: OSI Approved :: Apache Software License
Classifier: Natural Language :: English
Classifier: Programming Language :: Python :: 3.6
Classifier: Programming Language :: Python :: 3.7
Requires-Dist: python-twitter
Requires-Dist: pendulum
